sigpytch/__init__.py
sigpytch/forecasters.py
sigpytch/metrics.py
sigpytch/periods.py
sigpytch-1.1.2.dist-info/LICENSE
sigpytch-1.1.2.dist-info/METADATA
sigpytch-1.1.2.dist-info/WHEEL
sigpytch-1.1.2.dist-info/top_level.txt
sigpytch-1.1.2.dist-info/RECORD
